modules/__init__.py
modules/utils.py
seleniumHFAPI-0.1.0.dist-info/LICENSE
seleniumHFAPI-0.1.0.dist-info/METADATA
seleniumHFAPI-0.1.0.dist-info/WHEEL
seleniumHFAPI-0.1.0.dist-info/top_level.txt
seleniumHFAPI-0.1.0.dist-info/RECORD
