Metadata-Version: 2.1
Name: seleniumHFAPI
Version: 0.1.0
Summary: A Selenium-based API for Hugging Face interactions
Home-page: https://github.com/yourusername/seleniumHFAPI
Author: My Name
Author-email: your.email@example.com
Classifier: Programming Language :: Python :: 3
Classifier: License :: OSI Approved :: MIT License
Classifier: Operating System :: OS Independent
Requires-Python: >=3.6
License-File: LICENSE
Requires-Dist: selenium
Requires-Dist: gradio_client
